MANIFEST.in
README.rst
setup.py
geofdw/__init__.py
geofdw/_version.py
geofdw/base.py
geofdw/exception.py
geofdw/utils.py
geofdw.egg-info/PKG-INFO
geofdw.egg-info/SOURCES.txt
geofdw.egg-info/dependency_links.txt
geofdw.egg-info/requires.txt
geofdw.egg-info/top_level.txt
geofdw/fdw/__init__.py
geofdw/fdw/geocode.py
geofdw/fdw/geojson.py
geofdw/fdw/randompoint.py
test/test_exception.py
test/test_geofdw.py
test/test_utils.py