Metadata-Version: 1.0
Name: geofdw
Version: 0.0.3
Summary: Foreign Data Wrappers for PostGIS
Home-page: http://github.com/bosth/geofdw
Author: Benjamin Trigona-Harany
Author-email: bosth@alumni.sfu.ca
License: GNU GPLv3
Keywords: gis geographical postgis fdw postgresql
Platform: any
